iemail/__init__.py
iemail/exceptions.py
iemail/models.py
iemail/utils.py
iemail-1.1.dist-info/LICENSE
iemail-1.1.dist-info/METADATA
iemail-1.1.dist-info/WHEEL
iemail-1.1.dist-info/top_level.txt
iemail-1.1.dist-info/RECORD
