Metadata-Version: 2.1
Name: iemail
Version: 1.1
Summary: Temporary Email Python SDK of https://api.iemail.eu.org/
Home-page: https://pypi.org/project/iemail/
Author: IEmail
Author-email: i@iemail.eu.org
Project-URL: HomePage, https://iemail.eu.org/
Project-URL: API Gateway, https://api.iemail.eu.org/
Keywords: Tempmail mail iemail email API
Classifier: Intended Audience :: Developers
Classifier: License :: OSI Approved :: MIT License
Classifier: Programming Language :: Python :: 3
Classifier: Programming Language :: Python :: 3.6
Classifier: Programming Language :: Python :: 3.7
Classifier: Programming Language :: Python :: 3.8
Classifier: Programming Language :: Python :: 3.9
Classifier: Programming Language :: Python :: 3.10
Classifier: Programming Language :: Python :: 3.11
License-File: LICENSE
Requires-Dist: requests
